MANIFEST.in
setup.cfg
setup.py
jiesu_python_service/__init__.py
jiesu_python_service/service.py
jiesu_python_service.egg-info/PKG-INFO
jiesu_python_service.egg-info/SOURCES.txt
jiesu_python_service.egg-info/dependency_links.txt
jiesu_python_service.egg-info/not-zip-safe
jiesu_python_service.egg-info/requires.txt
jiesu_python_service.egg-info/top_level.txt