Metadata-Version: 2.1
Name: jiesu-python-service
Version: 1.18
Summary: A Python Service
Author: Jie Su
